<?xml version="1.0" ?>
<name>
 GTH
 </name>
<atom symbol="Ag" lmax="2">
<local Zeff="1" radius="0.65000000" C1="-2.37606096" C2="0.00000000" C3="0.00000000" C4="0.00000000"/>
<nonlocal l="0" radius="1.01270456" h00="0.89793134" h11="-0.74832297" h22="0.02978730" k00="0.00000000" k11="0.00000000" k22="0.00000000"/>
<nonlocal l="1" radius="1.23584202" h00="0.13008068" h11="-0.27749548" h22="0.00000000" k00="0.01969167" k11="-0.00682116" k22="0.00000000"/>
<nonlocal l="2" radius="1.01615913" h00="-0.03884235" h11="0.00000000" h22="0.00000000" k00="0.00945505" k11="0.00000000" k22="0.00000000"/>
</atom>
<atom symbol="Al" lmax="1">
<local Zeff="3" radius="0.45000000" C1="-8.49135116" C2="0.00000000" C3="0.00000000" C4="0.00000000"/>
<nonlocal l="0" radius="0.46010427" h00="5.08833953" h11="2.67969975" h22="0.00000000" k00="0.00000000" k11="0.00000000" k22="0.00000000"/>
<nonlocal l="1" radius="0.53674439" h00="2.19343827" h11="0.00000000" h22="0.00000000" k00="0.00615404" k11="0.00394694" k22="0.00000000"/>
</atom>
<atom symbol="Ar" lmax="1">
<local Zeff="8" radius="0.40000000" C1="-7.10000000" C2="0.00000000" C3="0.00000000" C4="0.00000000"/>
<nonlocal l="0" radius="0.31738081" h00="10.24948699" h11="5.60251627" h22="0.00000000" k00="0.00000000" k11="0.00000000" k22="0.00000000"/>
<nonlocal l="1" radius="0.35161921" h00="4.97880101" h11="0.00000000" h22="0.00000000" k00="0.01639467" k11="0.02917087" k22="0.00000000"/>
</atom>
<atom symbol="As" lmax="2">
<local Zeff="5" radius="0.52000000" C1="0.00000000" C2="0.00000000" C3="0.00000000" C4="0.00000000"/>
<nonlocal l="0" radius="0.45640025" h00="4.56076106" h11="1.69238876" h22="-1.37380421" k00="0.00000000" k11="0.00000000" k22="0.00000000"/>
<nonlocal l="1" radius="0.55056168" h00="1.81224664" h11="-0.64672658" h22="0.00000000" k00="0.05246616" k11="0.02056179" k22="0.00000000"/>
<nonlocal l="2" radius="0.68528272" h00="0.31237276" h11="0.00000000" h22="0.00000000" k00="0.00427335" k11="0.00000000" k22="0.00000000"/>
</atom>
<atom symbol="At" lmax="2">
<local Zeff="7" radius="0.58000000" C1="13.52041116" C2="0.00000000" C3="0.00000000" C4="0.00000000"/>
<nonlocal l="0" radius="0.62782694" h00="0.94555652" h11="-0.96590285" h22="-0.19042856" k00="0.00000000" k11="0.00000000" k22="0.00000000"/>
<nonlocal l="1" radius="0.70982320" h00="0.52707805" h11="-0.31882073" h22="0.00000000" k00="0.48077365" k11="-0.03495387" k22="0.00000000"/>
<nonlocal l="2" radius="0.83836499" h00="0.46894787" h11="0.00000000" h22="0.00000000" k00="0.03754438" k11="0.00000000" k22="0.00000000"/>
</atom>
<atom symbol="Au" lmax="1">
<local Zeff="1" radius="0.65000000" C1="-1.96371223" C2="-1.69812291" C3="0.00000000" C4="0.00000000"/>
<nonlocal l="0" radius="0.91930757" h00="1.53959915" h11="-0.46877861" h22="-0.79203890" k00="0.00000000" k11="0.00000000" k22="0.00000000"/>
<nonlocal l="1" radius="1.14035080" h00="0.47122943" h11="-0.49753827" h22="-0.20975780" k00="0.03934865" k11="0.13296969" k22="-0.15342717"/>
</atom>
<atom symbol="Ba" lmax="2">
<local Zeff="2" radius="1.20000000" C1="0.00000000" C2="0.00000000" C3="0.00000000" C4="0.00000000"/>
<nonlocal l="0" radius="1.01618684" h00="0.92259259" h11="0.76349489" h22="-0.33346493" k00="0.00000000" k11="0.00000000" k22="0.00000000"/>
<nonlocal l="1" radius="1.24987991" h00="0.44716820" h11="0.15108073" h22="0.00000000" k00="-0.04101721" k11="0.08879970" k22="0.00000000"/>
<nonlocal l="2" radius="0.93715823" h00="-0.71893382" h11="0.00000000" h22="0.00000000" k00="0.00532055" k11="0.00000000" k22="0.00000000"/>
</atom>
<atom symbol="Be" lmax="1">
<local Zeff="2" radius="0.73900865" C1="-2.59295078" C2="0.35483893" C3="0.00000000" C4="0.00000000"/>
<nonlocal l="0" radius="0.52879656" h00="3.06166591" h11="0.00000000" h22="0.00000000" k00="0.00000000" k11="0.00000000" k22="0.00000000"/>
<nonlocal l="1" radius="0.65815348" h00="0.09246196" h11="0.00000000" h22="0.00000000" k00="0.00012877" k11="0.00000000" k22="0.00000000"/>
</atom>
<atom symbol="Bi" lmax="2">
<local Zeff="5" radius="0.60500000" C1="6.67943714" C2="0.00000000" C3="0.00000000" C4="0.00000000"/>
<nonlocal l="0" radius="0.67885795" h00="1.37763378" h11="-0.51369691" h22="-0.47102813" k00="0.00000000" k11="0.00000000" k22="0.00000000"/>
<nonlocal l="1" radius="0.79867267" h00="0.65557809" h11="-0.40293219" h22="0.00000000" k00="0.30531353" k11="-0.02313366" k22="0.00000000"/>
<nonlocal l="2" radius="0.93468255" h00="0.37847579" h11="0.00000000" h22="0.00000000" k00="0.02921737" k11="0.00000000" k22="0.00000000"/>
</atom>
<atom symbol="Br" lmax="2">
<local Zeff="7" radius="0.50000000" C1="0.00000000" C2="0.00000000" C3="0.00000000" C4="0.00000000"/>
<nonlocal l="0" radius="0.42820734" h00="5.39883713" h11="1.82029205" h22="-1.32397392" k00="0.00000000" k11="0.00000000" k22="0.00000000"/>
<nonlocal l="1" radius="0.45532308" h00="3.10882269" h11="-0.63220188" h22="0.00000000" k00="0.07400663" k11="0.06878684" k22="0.00000000"/>
<nonlocal l="2" radius="0.55784727" h00="0.55590294" h11="0.00000000" h22="0.00000000" k00="0.00714446" k11="0.00000000" k22="0.00000000"/>
</atom>
<atom symbol="B" lmax="1">
<local Zeff="3" radius="0.43392956" C1="-5.57864173" C2="0.80425145" C3="0.00000000" C4="0.00000000"/>
<nonlocal l="0" radius="0.37384326" h00="6.23392822" h11="0.00000000" h22="0.00000000" k00="0.00000000" k11="0.00000000" k22="0.00000000"/>
<nonlocal l="1" radius="0.36039317" h00="0.00000000" h11="0.00000000" h22="0.00000000" k00="0.00087786" k11="0.00000000" k22="0.00000000"/>
</atom>
<atom symbol="Ca" lmax="2">
<local Zeff="2" radius="0.80000000" C1="0.00000000" C2="0.00000000" C3="0.00000000" C4="0.00000000"/>
<nonlocal l="0" radius="0.66973721" h00="1.64501442" h11="1.52349082" h22="0.29599634" k00="0.00000000" k11="0.00000000" k22="0.00000000"/>
<nonlocal l="1" radius="0.94647402" h00="0.58547893" h11="0.12632878" h22="0.00000000" k00="-0.00336201" k11="0.01277891" k22="0.00000000"/>
<nonlocal l="2" radius="0.52654998" h00="-3.03232095" h11="0.00000000" h22="0.00000000" k00="0.00081449" k11="0.00000000" k22="0.00000000"/>
</atom>
<atom symbol="Cd" lmax="2">
<local Zeff="2" radius="0.62500000" C1="-1.79683799" C2="0.00000000" C3="0.00000000" C4="0.00000000"/>
<nonlocal l="0" radius="0.82846467" h00="1.48529241" h11="-0.42475283" h22="-0.40798627" k00="0.00000000" k11="0.00000000" k22="0.00000000"/>
<nonlocal l="1" radius="0.97287254" h00="0.46920843" h11="-0.44811107" h22="0.00000000" k00="0.03771366" k11="-0.00200856" k22="0.00000000"/>
<nonlocal l="2" radius="1.24094900" h00="0.06541164" h11="0.00000000" h22="0.00000000" k00="0.00310866" k11="0.00000000" k22="0.00000000"/>
</atom>
<atom symbol="Ce" lmax="3">
<local Zeff="12" radius="0.53500000" C1="18.84746984" C2="-0.76563607" C3="0.00000000" C4="0.00000000"/>
<nonlocal l="0" radius="0.52179048" h00="1.32161643" h11="-1.70044394" h22="0.00000000" k00="0.00000000" k11="0.00000000" k22="0.00000000"/>
<nonlocal l="1" radius="0.47032440" h00="0.97264077" h11="-1.45133651" h22="0.00000000" k00="0.46370953" k11="0.09025691" k22="0.01256583"/>
<nonlocal l="2" radius="0.70359268" h00="0.07424079" h11="0.00000000" h22="0.00000000" k00="0.01326523" k11="0.00000000" k22="0.00000000"/>
<nonlocal l="3" radius="0.30671668" h00="-17.21478997" h11="0.00000000" h22="0.00000000" k00="0.00756841" k11="0.00000000" k22="0.00000000"/>
</atom>
<atom symbol="Cl" lmax="1">
<local Zeff="7" radius="0.41000000" C1="-6.86475431" C2="0.00000000" C3="0.00000000" C4="0.00000000"/>
<nonlocal l="0" radius="0.33820832" h00="9.06223968" h11="5.06568240" h22="0.00000000" k00="0.00000000" k11="0.00000000" k22="0.00000000"/>
<nonlocal l="1" radius="0.37613709" h00="4.46587640" h11="0.00000000" h22="0.00000000" k00="0.01002014" k11="0.02578435" k22="0.00000000"/>
</atom>
<atom symbol="Co" lmax="2">
<local Zeff="9" radius="0.58000000" C1="0.00000000" C2="0.00000000" C3="0.00000000" C4="0.00000000"/>
<nonlocal l="0" radius="0.44045735" h00="3.33497825" h11="2.87315017" h22="3.09102805" k00="0.00000000" k11="0.00000000" k22="0.00000000"/>
<nonlocal l="1" radius="0.61004847" h00="1.63400481" h11="0.35608316" h22="0.00000000" k00="-0.01752129" k11="0.05876575" k22="0.00000000"/>
<nonlocal l="2" radius="0.29166058" h00="-10.35880017" h11="0.00000000" h22="0.00000000" k00="0.00713682" k11="0.00000000" k22="0.00000000"/>
</atom>
<atom symbol="Cr" lmax="2">
<local Zeff="6" radius="0.66000000" C1="0.00000000" C2="0.00000000" C3="0.00000000" C4="0.00000000"/>
<nonlocal l="0" radius="0.49857767" h00="2.40075556" h11="2.07233658" h22="2.95217934" k00="0.00000000" k11="0.00000000" k22="0.00000000"/>
<nonlocal l="1" radius="0.71976824" h00="1.14555658" h11="0.27823604" h22="0.00000000" k00="-0.01317649" k11="0.03562545" k22="0.00000000"/>
<nonlocal l="2" radius="0.35434060" h00="-6.61587832" h11="0.00000000" h22="0.00000000" k00="0.00351409" k11="0.00000000" k22="0.00000000"/>
</atom>
<atom symbol="Cs" lmax="2">
<local Zeff="1" radius="1.20000000" C1="0.00000000" C2="0.00000000" C3="0.00000000" C4="0.00000000"/>
<nonlocal l="0" radius="1.22473727" h00="0.61152657" h11="0.23983005" h22="-0.29402418" k00="0.00000000" k11="0.00000000" k22="0.00000000"/>
<nonlocal l="1" radius="1.28047759" h00="0.24489277" h11="0.22727863" h22="0.00000000" k00="-0.10762747" k11="0.13813185" k22="0.00000000"/>
<nonlocal l="2" radius="1.10752212" h00="-0.54216260" h11="0.00000000" h22="0.00000000" k00="0.00325918" k11="0.00000000" k22="0.00000000"/>
</atom>
<atom symbol="Cu" lmax="2">
<local Zeff="1" radius="0.58000000" C1="0.00000000" C2="0.00000000" C3="0.00000000" C4="0.00000000"/>
<nonlocal l="0" radius="0.84328288" h00="0.97578662" h11="-0.82206962" h22="-0.13323707" k00="0.00000000" k11="0.00000000" k22="0.00000000"/>
<nonlocal l="1" radius="1.08954266" h00="0.02457986" h11="-0.24900093" h22="0.00000000" k00="0.01079247" k11="-0.00673399" k22="0.00000000"/>
<nonlocal l="2" radius="1.29160225" h00="-0.06529209" h11="0.00000000" h22="0.00000000" k00="-0.00073000" k11="0.00000000" k22="0.00000000"/>
</atom>
<atom symbol="C" lmax="1">
<local Zeff="4" radius="0.34883045" C1="-8.51377110" C2="1.22843203" C3="0.00000000" C4="0.00000000"/>
<nonlocal l="0" radius="0.30455321" h00="9.52284179" h11="0.00000000" h22="0.00000000" k00="0.00000000" k11="0.00000000" k22="0.00000000"/>
<nonlocal l="1" radius="0.23267730" h00="0.00000000" h11="0.00000000" h22="0.00000000" k00="0.00410365" k11="0.00000000" k22="0.00000000"/>
</atom>
<atom symbol="Dy" lmax="3">
<local Zeff="20" radius="0.51166666" C1="16.99433138" C2="-0.95529792" C3="0.00000000" C4="0.00000000"/>
<nonlocal l="0" radius="0.44059045" h00="1.94031950" h11="-3.55979777" h22="0.00000000" k00="0.00000000" k11="0.00000000" k22="0.00000000"/>
<nonlocal l="1" radius="0.43464206" h00="0.01431536" h11="-2.04623793" h22="0.00000000" k00="-0.12437116" k11="1.32740399" k22="-1.09214158"/>
<nonlocal l="2" radius="0.46722880" h00="-0.66892417" h11="0.00000000" h22="0.00000000" k00="0.05828571" k11="0.00000000" k22="0.00000000"/>
<nonlocal l="3" radius="0.26167045" h00="-23.92235817" h11="0.00000000" h22="0.00000000" k00="0.01793827" k11="0.00000000" k22="0.00000000"/>
</atom>
<atom symbol="Er" lmax="3">
<local Zeff="22" radius="0.50583333" C1="17.10529281" C2="-1.43095318" C3="0.00000000" C4="0.00000000"/>
<nonlocal l="0" radius="0.41994801" h00="2.14450257" h11="-3.98420323" h22="0.00000000" k00="0.00000000" k11="0.00000000" k22="0.00000000"/>
<nonlocal l="1" radius="0.41445530" h00="0.05408736" h11="-2.29447680" h22="0.00000000" k00="1.25513474" k11="-0.89196004" k22="0.74971696"/>
<nonlocal l="2" radius="0.41838497" h00="-0.99900632" h11="0.00000000" h22="0.00000000" k00="0.09186175" k11="0.00000000" k22="0.00000000"/>
<nonlocal l="3" radius="0.24912591" h00="-26.69680936" h11="0.00000000" h22="0.00000000" k00="0.02178337" k11="0.00000000" k22="0.00000000"/>
</atom>
<atom symbol="Eu" lmax="3">
<local Zeff="17" radius="0.52041668" C1="17.37351625" C2="-0.64846778" C3="0.00000000" C4="0.00000000"/>
<nonlocal l="0" radius="0.46904261" h00="1.76363790" h11="-2.91693172" h22="0.00000000" k00="0.00000000" k11="0.00000000" k22="0.00000000"/>
<nonlocal l="1" radius="0.44590722" h00="0.51804594" h11="-2.13518554" h22="0.00000000" k00="0.25225840" k11="0.58432399" k22="-0.48058621"/>
<nonlocal l="2" radius="0.49003840" h00="-0.42611996" h11="0.00000000" h22="0.00000000" k00="0.05102753" k11="0.00000000" k22="0.00000000"/>
<nonlocal l="3" radius="0.27840129" h00="-20.94652763" h11="0.00000000" h22="0.00000000" k00="0.01326718" k11="0.00000000" k22="0.00000000"/>
</atom>
<atom symbol="Fe" lmax="2">
<local Zeff="8" radius="0.61000000" C1="0.00000000" C2="0.00000000" C3="0.00000000" C4="0.00000000"/>
<nonlocal l="0" radius="0.45448200" h00="3.01664046" h11="2.58303836" h22="3.25763534" k00="0.00000000" k11="0.00000000" k22="0.00000000"/>
<nonlocal l="1" radius="0.63890282" h00="1.49964199" h11="0.32687369" h22="0.00000000" k00="-0.01490858" k11="0.04979310" k22="0.00000000"/>
<nonlocal l="2" radius="0.30873177" h00="-9.14535371" h11="0.00000000" h22="0.00000000" k00="0.00572210" k11="0.00000000" k22="0.00000000"/>
</atom>
<atom symbol="F" lmax="1">
<local Zeff="7" radius="0.21852465" C1="-21.30736112" C2="3.07286942" C3="0.00000000" C4="0.00000000"/>
<nonlocal l="0" radius="0.19556721" h00="23.58494211" h11="0.00000000" h22="0.00000000" k00="0.00000000" k11="0.00000000" k22="0.00000000"/>
<nonlocal l="1" radius="0.17426832" h00="0.00000000" h11="0.00000000" h22="0.00000000" k00="0.01510589" k11="0.00000000" k22="0.00000000"/>
</atom>
<atom symbol="Ga" lmax="2">
<local Zeff="3" radius="0.56000000" C1="0.00000000" C2="0.00000000" C3="0.00000000" C4="0.00000000"/>
<nonlocal l="0" radius="0.61079074" h00="2.36932516" h11="-0.24901512" h22="-0.55179624" k00="0.00000000" k11="0.00000000" k22="0.00000000"/>
<nonlocal l="1" radius="0.70459583" h00="0.74630529" h11="-0.51313234" h22="0.00000000" k00="0.02960710" k11="-0.00087320" k22="0.00000000"/>
<nonlocal l="2" radius="0.98257967" h00="0.07543656" h11="0.00000000" h22="0.00000000" k00="0.00148617" k11="0.00000000" k22="0.00000000"/>
</atom>
<atom symbol="Gd" lmax="3">
<local Zeff="18" radius="0.51750004" C1="17.51255640" C2="-0.71953420" C3="0.00000000" C4="0.00000000"/>
<nonlocal l="0" radius="0.46201372" h00="1.55185591" h11="-3.06870256" h22="0.00000000" k00="0.00000000" k11="0.00000000" k22="0.00000000"/>
<nonlocal l="1" radius="0.45695327" h00="-0.05834713" h11="-1.69771095" h22="0.00000000" k00="0.53553977" k11="0.02202404" k22="-0.05430110"/>
<nonlocal l="2" radius="0.48236813" h00="-0.56260077" h11="0.00000000" h22="0.00000000" k00="0.05312761" k11="0.00000000" k22="0.00000000"/>
<nonlocal l="3" radius="0.27338980" h00="-21.92349011" h11="0.00000000" h22="0.00000000" k00="0.01466612" k11="0.00000000" k22="0.00000000"/>
</atom>
<atom symbol="Ge" lmax="2">
<local Zeff="4" radius="0.54000000" C1="0.00000000" C2="0.00000000" C3="0.00000000" C4="0.00000000"/>
<nonlocal l="0" radius="0.49374254" h00="3.82689099" h11="1.10023129" h22="-1.34421765" k00="0.00000000" k11="0.00000000" k22="0.00000000"/>
<nonlocal l="1" radius="0.60106438" h00="1.36251781" h11="-0.62736987" h22="0.00000000" k00="0.04398121" k11="0.00980152" k22="0.00000000"/>
<nonlocal l="2" radius="0.78836851" h00="0.19120485" h11="0.00000000" h22="0.00000000" k00="0.00291785" k11="0.00000000" k22="0.00000000"/>
</atom>
<atom symbol="He" lmax="-1">
<local Zeff="2" radius="0.20000000" C1="-9.11202340" C2="1.69836797" C3="0.00000000" C4="0.00000000"/>
</atom>
<atom symbol="Hf" lmax="2">
<local Zeff="12" radius="0.56000000" C1="5.13480056" C2="0.52919062" C3="0.00000000" C4="0.00000000"/>
<nonlocal l="0" radius="0.42281035" h00="2.56444209" h11="-6.01373234" h22="1.10975964" k00="0.00000000" k11="0.00000000" k22="0.00000000"/>
<nonlocal l="1" radius="0.47268130" h00="-1.02527490" h11="-1.87254839" h22="0.00000000" k00="0.60750427" k11="-0.33163669" k22="-0.12102083"/>
<nonlocal l="2" radius="0.42638752" h00="1.45936326" h11="-5.28276448" h22="0.00000000" k00="0.22211861" k11="-0.12128275" k22="0.00000000"/>
</atom>
<atom symbol="Hg" lmax="2">
<local Zeff="2" radius="0.64000000" C1="-3.29632880" C2="0.00000000" C3="0.00000000" C4="0.00000000"/>
<nonlocal l="0" radius="0.81210780" h00="1.76504143" h11="-0.46612737" h22="-0.79994085" k00="0.00000000" k11="0.00000000" k22="0.00000000"/>
<nonlocal l="1" radius="1.05371378" h00="0.47405588" h11="-0.53181582" h22="0.00000000" k00="0.09232980" k11="-0.00111786" k22="0.00000000"/>
<nonlocal l="2" radius="1.10000000" h00="0.12063831" h11="0.00000000" h22="0.00000000" k00="0.02093075" k11="0.00000000" k22="0.00000000"/>
</atom>
<atom symbol="Ho" lmax="3">
<local Zeff="21" radius="0.50875002" C1="16.78157003" C2="-1.17351448" C3="0.00000000" C4="0.00000000"/>
<nonlocal l="0" radius="0.43221176" h00="2.05279689" h11="-3.67453429" h22="0.00000000" k00="0.00000000" k11="0.00000000" k22="0.00000000"/>
<nonlocal l="1" radius="0.42013792" h00="0.25329464" h11="-2.35528878" h22="0.00000000" k00="0.89594677" k11="-0.27514887" k22="0.20572910"/>
<nonlocal l="2" radius="0.44713057" h00="-0.74286267" h11="0.00000000" h22="0.00000000" k00="0.06948258" k11="0.00000000" k22="0.00000000"/>
<nonlocal l="3" radius="0.25499226" h00="-25.19721081" h11="0.00000000" h22="0.00000000" k00="0.01983007" k11="0.00000000" k22="0.00000000"/>
</atom>
<atom symbol="H" lmax="-1">
<local Zeff="1" radius="0.20000000" C1="-4.18023680" C2="0.72507482" C3="0.00000000" C4="0.00000000"/>
</atom>
<atom symbol="In" lmax="2">
<local Zeff="3" radius="0.61000000" C1="2.86577676" C2="0.00000000" C3="0.00000000" C4="0.00000000"/>
<nonlocal l="0" radius="0.77060197" h00="1.25619360" h11="-0.39725499" h22="-0.27832906" k00="0.00000000" k11="0.00000000" k22="0.00000000"/>
<nonlocal l="1" radius="0.85813160" h00="0.49445864" h11="-0.38078878" h22="0.00000000" k00="0.06636653" k11="-0.00556265" k22="0.00000000"/>
<nonlocal l="2" radius="1.08869090" h00="0.12920778" h11="0.00000000" h22="0.00000000" k00="0.00444800" k11="0.00000000" k22="0.00000000"/>
</atom>
<atom symbol="Ir" lmax="2">
<local Zeff="9" radius="0.64100000" C1="10.72001591" C2="0.00000000" C3="0.00000000" C4="0.00000000"/>
<nonlocal l="0" radius="0.50996044" h00="2.44599887" h11="2.81103736" h22="0.00000000" k00="0.00000000" k11="0.00000000" k22="0.00000000"/>
<nonlocal l="1" radius="0.68497052" h00="0.46179182" h11="1.30472563" h22="0.00000000" k00="-0.56534735" k11="0.85962018" k22="0.00000000"/>
<nonlocal l="2" radius="0.47174528" h00="-4.54548411" h11="-1.63542847" h22="0.00000000" k00="0.12719880" k11="-0.15194970" k22="0.00000000"/>
</atom>
<atom symbol="I" lmax="2">
<local Zeff="7" radius="0.56000000" C1="14.66182521" C2="0.00000000" C3="0.00000000" C4="0.00000000"/>
<nonlocal l="0" radius="0.55283008" h00="1.33805374" h11="-0.83485108" h22="-0.46743768" k00="0.00000000" k11="0.00000000" k22="0.00000000"/>
<nonlocal l="1" radius="0.56225147" h00="0.67449617" h11="-0.57778676" h22="0.00000000" k00="0.21396743" k11="0.09331314" k22="0.00000000"/>
<nonlocal l="2" radius="0.79432495" h00="0.22434543" h11="0.00000000" h22="0.00000000" k00="0.01018039" k11="0.00000000" k22="0.00000000"/>
</atom>
<atom symbol="Kr" lmax="2">
<local Zeff="8" radius="0.50000000" C1="0.00000000" C2="0.00000000" C3="0.00000000" C4="0.00000000"/>
<nonlocal l="0" radius="0.41075893" h00="5.91119429" h11="1.96737236" h22="-1.45806869" k00="0.00000000" k11="0.00000000" k22="0.00000000"/>
<nonlocal l="1" radius="0.43025641" h00="3.52435692" h11="-0.69119763" h22="0.00000000" k00="0.08701098" k11="0.08600750" k22="0.00000000"/>
<nonlocal l="2" radius="0.51712005" h00="0.62922850" h11="0.00000000" h22="0.00000000" k00="0.00926681" k11="0.00000000" k22="0.00000000"/>
</atom>
<atom symbol="K" lmax="2">
<local Zeff="1" radius="0.95000000" C1="0.00000000" C2="0.00000000" C3="0.00000000" C4="0.00000000"/>
<nonlocal l="0" radius="0.95536395" h00="0.91461200" h11="0.28755094" h22="-0.30022386" k00="0.00000000" k11="0.00000000" k22="0.00000000"/>
<nonlocal l="1" radius="1.08641063" h00="0.31546177" h11="0.06819410" h22="0.00000000" k00="-0.00434261" k11="0.01026146" k22="0.00000000"/>
<nonlocal l="2" radius="0.72060608" h00="-1.52951361" h11="0.00000000" h22="0.00000000" k00="0.00035395" k11="0.00000000" k22="0.00000000"/>
</atom>
<atom symbol="La" lmax="3">
<local Zeff="11" radius="0.53500000" C1="19.90930823" C2="-1.47483023" C3="0.00000000" C4="0.00000000"/>
<nonlocal l="0" radius="0.55177542" h00="1.29327192" h11="-1.12181937" h22="0.00000000" k00="0.00000000" k11="0.00000000" k22="0.00000000"/>
<nonlocal l="1" radius="0.47630806" h00="1.17252682" h11="-0.82880986" h22="0.02985728" k00="0.52462281" k11="-0.03090129" k22="0.14207685"/>
<nonlocal l="2" radius="0.62667220" h00="0.32837704" h11="0.00000000" h22="0.00000000" k00="0.02089998" k11="0.00000000" k22="0.00000000"/>
<nonlocal l="3" radius="0.29931017" h00="-18.26943896" h11="0.00000000" h22="0.00000000" k00="0.00719271" k11="0.00000000" k22="0.00000000"/>
</atom>
<atom symbol="Li" lmax="1">
<local Zeff="1" radius="0.78755305" C1="-1.89261247" C2="0.28605968" C3="0.00000000" C4="0.00000000"/>
<nonlocal l="0" radius="0.66637518" h00="1.85881111" h11="0.00000000" h22="0.00000000" k00="0.00000000" k11="0.00000000" k22="0.00000000"/>
<nonlocal l="1" radius="1.07930561" h00="-0.00589504" h11="0.00000000" h22="0.00000000" k00="0.00001876" k11="0.00000000" k22="0.00000000"/>
</atom>
<atom symbol="Lu" lmax="3">
<local Zeff="25" radius="0.49700000" C1="17.03705292" C2="-1.66161023" C3="0.00000000" C4="0.00000000"/>
<nonlocal l="0" radius="0.39120615" h00="2.18467779" h11="-5.43234610" h22="0.00000000" k00="0.00000000" k11="0.00000000" k22="0.00000000"/>
<nonlocal l="1" radius="0.39389567" h00="-0.71981878" h11="-2.72379890" h22="0.00000000" k00="0.15245040" k11="1.39541622" k22="-1.23874407"/>
<nonlocal l="2" radius="0.43651827" h00="-1.17324513" h11="0.00000000" h22="0.00000000" k00="0.07213023" k11="0.00000000" k22="0.00000000"/>
<nonlocal l="3" radius="0.23262926" h00="-31.85226177" h11="0.00000000" h22="0.00000000" k00="0.02800562" k11="0.00000000" k22="0.00000000"/>
</atom>
<atom symbol="Mg" lmax="1">
<local Zeff="2" radius="0.65181169" C1="-2.86429746" C2="0.00000000" C3="0.00000000" C4="0.00000000"/>
<nonlocal l="0" radius="0.55647814" h00="2.97095712" h11="1.32994091" h22="0.00000000" k00="0.00000000" k11="0.00000000" k22="0.00000000"/>
<nonlocal l="1" radius="0.67756881" h00="1.04988101" h11="0.00000000" h22="0.00000000" k00="0.00515157" k11="0.00000000" k22="0.00000000"/>
</atom>
<atom symbol="Mn" lmax="2">
<local Zeff="7" radius="0.64000000" C1="0.00000000" C2="0.00000000" C3="0.00000000" C4="0.00000000"/>
<nonlocal l="0" radius="0.48124608" h00="2.79903057" h11="2.48610107" h22="2.56562982" k00="0.00000000" k11="0.00000000" k22="0.00000000"/>
<nonlocal l="1" radius="0.66930432" h00="1.36877564" h11="0.31676337" h22="0.00000000" k00="-0.01368526" k11="0.04293805" k22="0.00000000"/>
<nonlocal l="2" radius="0.32776314" h00="-7.99541784" h11="0.00000000" h22="0.00000000" k00="0.00453641" k11="0.00000000" k22="0.00000000"/>
</atom>
<atom symbol="Mo" lmax="2">
<local Zeff="6" radius="0.69900000" C1="7.99586821" C2="0.00000000" C3="0.00000000" C4="0.00000000"/>
<nonlocal l="0" radius="0.67812595" h00="1.28960728" h11="0.99811301" h22="0.00000000" k00="0.00000000" k11="0.00000000" k22="0.00000000"/>
<nonlocal l="1" radius="0.80077140" h00="0.30141226" h11="0.74161451" h22="0.00000000" k00="-0.10412389" k11="0.15390632" k22="0.00000000"/>
<nonlocal l="2" radius="0.45338393" h00="-2.80970771" h11="-6.82094635" h22="0.00000000" k00="0.06897223" k11="-0.07559069" k22="0.00000000"/>
</atom>
<atom symbol="Na" lmax="1">
<local Zeff="1" radius="0.88550938" C1="-1.23886713" C2="0.00000000" C3="0.00000000" C4="0.00000000"/>
<nonlocal l="0" radius="0.66110390" h00="1.84727135" h11="0.58200362" h22="0.00000000" k00="0.00000000" k11="0.00000000" k22="0.00000000"/>
<nonlocal l="1" radius="0.85711928" h00="0.47113258" h11="0.00000000" h22="0.00000000" k00="0.00262341" k11="0.00000000" k22="0.00000000"/>
</atom>
<atom symbol="Nb" lmax="2">
<local Zeff="5" radius="0.72400000" C1="4.02105754" C2="0.00000000" C3="0.00000000" C4="0.00000000"/>
<nonlocal l="0" radius="0.69970828" h00="1.53265135" h11="1.42826399" h22="0.00000000" k00="0.00000000" k11="0.00000000" k22="0.00000000"/>
<nonlocal l="1" radius="0.84667164" h00="0.60967518" h11="0.59678759" h22="0.00000000" k00="-0.08081558" k11="0.12524320" k22="0.00000000"/>
<nonlocal l="2" radius="0.51607226" h00="-2.69682993" h11="-1.69496657" h22="0.00000000" k00="0.02565344" k11="-0.03154090" k22="0.00000000"/>
</atom>
<atom symbol="Nd" lmax="3">
<local Zeff="14" radius="0.52916670" C1="17.81503043" C2="-0.59479767" C3="0.00000000" C4="0.00000000"/>
<nonlocal l="0" radius="0.50299986" h00="1.52910988" h11="-2.15373194" h22="0.00000000" k00="0.00000000" k11="0.00000000" k22="0.00000000"/>
<nonlocal l="1" radius="0.46701290" h00="0.72155346" h11="-1.64749920" h22="0.00000000" k00="-0.21439589" k11="1.10044645" k22="-0.83266969"/>
<nonlocal l="2" radius="0.32528958" h00="-0.54324017" h11="0.00000000" h22="0.00000000" k00="0.61141305" k11="0.00000000" k22="0.00000000"/>
<nonlocal l="3" radius="0.29474281" h00="-18.52022760" h11="0.00000000" h22="0.00000000" k00="0.00959761" k11="0.00000000" k22="0.00000000"/>
</atom>
<atom symbol="Ne" lmax="1">
<local Zeff="8" radius="0.19000000" C1="-27.69285182" C2="4.00590585" C3="0.00000000" C4="0.00000000"/>
<nonlocal l="0" radius="0.17948804" h00="28.50609828" h11="-1.07624528" h22="0.00000000" k00="0.00000000" k11="0.00000000" k22="0.00000000"/>
<nonlocal l="1" radius="0.21491271" h00="-0.00008991" h11="0.00000000" h22="0.00000000" k00="0.01033644" k11="0.00000000" k22="0.00000000"/>
</atom>
<atom symbol="Ni" lmax="2">
<local Zeff="10" radius="0.56000000" C1="0.00000000" C2="0.00000000" C3="0.00000000" C4="0.00000000"/>
<nonlocal l="0" radius="0.42539870" h00="3.61965071" h11="3.08896496" h22="3.05859831" k00="0.00000000" k11="0.00000000" k22="0.00000000"/>
<nonlocal l="1" radius="0.58408076" h00="1.74222007" h11="0.38634067" h22="0.00000000" k00="-0.02038398" k11="0.06877038" k22="0.00000000"/>
<nonlocal l="2" radius="0.27811348" h00="-11.60842823" h11="0.00000000" h22="0.00000000" k00="0.00870832" k11="0.00000000" k22="0.00000000"/>
</atom>
<atom symbol="N" lmax="1">
<local Zeff="5" radius="0.28917923" C1="-12.23481988" C2="1.76640728" C3="0.00000000" C4="0.00000000"/>
<nonlocal l="0" radius="0.25660487" h00="13.55224272" h11="0.00000000" h22="0.00000000" k00="0.00000000" k11="0.00000000" k22="0.00000000"/>
<nonlocal l="1" radius="0.27013369" h00="0.00000000" h11="0.00000000" h22="0.00000000" k00="0.00313068" k11="0.00000000" k22="0.00000000"/>
</atom>
<atom symbol="Os" lmax="2">
<local Zeff="8" radius="0.66700000" C1="9.44045936" C2="0.00000000" C3="0.00000000" C4="0.00000000"/>
<nonlocal l="0" radius="0.51030708" h00="2.40236688" h11="3.04670577" h22="0.00000000" k00="0.00000000" k11="0.00000000" k22="0.00000000"/>
<nonlocal l="1" radius="0.71755329" h00="0.49952321" h11="1.05328427" h22="0.00000000" k00="-0.43074635" k11="0.70175157" k22="0.00000000"/>
<nonlocal l="2" radius="0.48758605" h00="-4.14203471" h11="-1.66610013" h22="0.00000000" k00="0.11694065" k11="-0.13976139" k22="0.00000000"/>
</atom>
<atom symbol="O" lmax="1">
<local Zeff="6" radius="0.24762086" C1="-16.58031797" C2="2.39570092" C3="0.00000000" C4="0.00000000"/>
<nonlocal l="0" radius="0.22178614" h00="18.26691718" h11="0.00000000" h22="0.00000000" k00="0.00000000" k11="0.00000000" k22="0.00000000"/>
<nonlocal l="1" radius="0.25682890" h00="0.00000000" h11="0.00000000" h22="0.00000000" k00="0.00447578" k11="0.00000000" k22="0.00000000"/>
</atom>
<atom symbol="Pb" lmax="2">
<local Zeff="4" radius="0.61750000" C1="0.75314257" C2="0.00000000" C3="0.00000000" C4="0.00000000"/>
<nonlocal l="0" radius="0.70525860" h00="1.97992741" h11="-0.16495996" h22="-0.80606040" k00="0.00000000" k11="0.00000000" k22="0.00000000"/>
<nonlocal l="1" radius="0.84664106" h00="0.86442030" h11="-0.54096885" h22="0.00000000" k00="0.20771072" k11="0.01294813" k22="0.00000000"/>
<nonlocal l="2" radius="0.97193857" h00="0.37496708" h11="0.00000000" h22="0.00000000" k00="0.02925557" k11="0.00000000" k22="0.00000000"/>
</atom>
<atom symbol="Pd" lmax="2">
<local Zeff="10" radius="0.59600000" C1="5.20966476" C2="0.00000000" C3="0.00000000" C4="0.00000000"/>
<nonlocal l="0" radius="0.58220422" h00="2.41107608" h11="2.31892024" h22="0.00000000" k00="0.00000000" k11="0.00000000" k22="0.00000000"/>
<nonlocal l="1" radius="0.68878713" h00="1.22725330" h11="0.75802053" h22="0.00000000" k00="-0.13690890" k11="0.22080482" k22="0.00000000"/>
<nonlocal l="2" radius="0.44283523" h00="-4.37713124" h11="0.41327105" h22="0.00000000" k00="0.03379697" k11="-0.04779814" k22="0.00000000"/>
</atom>
<atom symbol="Pm" lmax="3">
<local Zeff="15" radius="0.52625000" C1="18.25172292" C2="-0.49210744" C3="0.00000000" C4="0.00000000"/>
<nonlocal l="0" radius="0.48987856" h00="1.30897757" h11="-2.50775088" h22="0.00000000" k00="0.00000000" k11="0.00000000" k22="0.00000000"/>
<nonlocal l="1" radius="0.47226016" h00="0.16051238" h11="-1.56530527" h22="0.00000000" k00="-0.33995543" k11="1.35901707" k22="-1.14588259"/>
<nonlocal l="2" radius="0.47370914" h00="-0.42995241" h11="0.00000000" h22="0.00000000" k00="0.06404352" k11="0.00000000" k22="0.00000000"/>
<nonlocal l="3" radius="0.29152653" h00="-19.30505668" h11="0.00000000" h22="0.00000000" k00="0.01061852" k11="0.00000000" k22="0.00000000"/>
</atom>
<atom symbol="Po" lmax="2">
<local Zeff="6" radius="0.59250000" C1="10.41173070" C2="0.00000000" C3="0.00000000" C4="0.00000000"/>
<nonlocal l="0" radius="0.64794961" h00="1.14420296" h11="-0.73585149" h22="-0.33938616" k00="0.00000000" k11="0.00000000" k22="0.00000000"/>
<nonlocal l="1" radius="0.74894708" h00="0.59456184" h11="-0.35359482" h22="0.00000000" k00="0.39635435" k11="-0.03146213" k22="0.00000000"/>
<nonlocal l="2" radius="0.88046840" h00="0.43323228" h11="0.00000000" h22="0.00000000" k00="0.03388641" k11="0.00000000" k22="0.00000000"/>
</atom>
<atom symbol="Pr" lmax="3">
<local Zeff="13" radius="0.53208333" C1="18.42473909" C2="-0.65766893" C3="0.00000000" C4="0.00000000"/>
<nonlocal l="0" radius="0.52684996" h00="1.01262106" h11="-1.71798165" h22="0.00000000" k00="0.00000000" k11="0.00000000" k22="0.00000000"/>
<nonlocal l="1" radius="0.45889736" h00="1.11706004" h11="-1.85210872" h22="0.00000000" k00="0.31427984" k11="0.35098185" k22="-0.16525431"/>
<nonlocal l="2" radius="0.74760989" h00="0.01757109" h11="0.00000000" h22="0.00000000" k00="0.01090482" k11="0.00000000" k22="0.00000000"/>
<nonlocal l="3" radius="0.30077296" h00="-17.89711891" h11="0.00000000" h22="0.00000000" k00="0.00854696" k11="0.00000000" k22="0.00000000"/>
</atom>
<atom symbol="Pt" lmax="2">
<local Zeff="10" radius="0.61600000" C1="11.02741707" C2="0.00000000" C3="0.00000000" C4="0.00000000"/>
<nonlocal l="0" radius="0.52013211" h00="2.44743006" h11="2.64035978" h22="0.00000000" k00="0.00000000" k11="0.00000000" k22="0.00000000"/>
<nonlocal l="1" radius="0.65897566" h00="0.40845297" h11="1.64771604" h22="0.00000000" k00="-0.76329581" k11="1.06588325" k22="0.00000000"/>
<nonlocal l="2" radius="0.45124318" h00="-4.55229454" h11="-2.10239568" h22="0.00000000" k00="0.14691239" k11="-0.16930645" k22="0.00000000"/>
</atom>
<atom symbol="P" lmax="1">
<local Zeff="5" radius="0.43000000" C1="-6.65421981" C2="0.00000000" C3="0.00000000" C4="0.00000000"/>
<nonlocal l="0" radius="0.38980284" h00="6.84213556" h11="3.85669332" h22="0.00000000" k00="0.00000000" k11="0.00000000" k22="0.00000000"/>
<nonlocal l="1" radius="0.44079585" h00="3.28260592" h11="0.00000000" h22="0.00000000" k00="0.00254425" k11="0.01789537" k22="0.00000000"/>
</atom>
<atom symbol="Rb" lmax="2">
<local Zeff="1" radius="1.09620685" C1="0.84733274" C2="-0.74812032" C3="0.00000000" C4="0.00000000"/>
<nonlocal l="0" radius="0.95569909" h00="0.88746022" h11="0.90308815" h22="-0.00675003" k00="0.00000000" k11="0.00000000" k22="0.00000000"/>
<nonlocal l="1" radius="1.15668058" h00="0.46173448" h11="0.33611273" h22="0.00000000" k00="-0.04344330" k11="0.05787561" k22="0.00000000"/>
<nonlocal l="2" radius="0.66432256" h00="-1.36293829" h11="0.00000000" h22="0.00000000" k00="0.00370757" k11="0.00000000" k22="0.00000000"/>
</atom>
<atom symbol="Re" lmax="2">
<local Zeff="7" radius="0.69300000" C1="8.18081618" C2="0.00000000" C3="0.00000000" C4="0.00000000"/>
<nonlocal l="0" radius="0.50981621" h00="2.26937936" h11="3.52852934" h22="0.00000000" k00="0.00000000" k11="0.00000000" k22="0.00000000"/>
<nonlocal l="1" radius="0.74583906" h00="0.49669329" h11="0.92582911" h22="0.00000000" k00="-0.37058909" k11="0.61676466" k22="0.00000000"/>
<nonlocal l="2" radius="0.50095420" h00="-3.68962967" h11="-1.89460099" h22="0.00000000" k00="0.11155664" k11="-0.13159543" k22="0.00000000"/>
</atom>
<atom symbol="Rh" lmax="2">
<local Zeff="9" radius="0.62142857" C1="5.39796233" C2="0.00000000" C3="0.00000000" C4="0.00000000"/>
<nonlocal l="0" radius="0.59807881" h00="2.24211131" h11="2.15159669" h22="0.00000000" k00="0.00000000" k11="0.00000000" k22="0.00000000"/>
<nonlocal l="1" radius="0.70958567" h00="1.15527830" h11="0.70484635" h22="0.00000000" k00="-0.11435695" k11="0.19392318" k22="0.00000000"/>
<nonlocal l="2" radius="0.36920687" h00="-1.05305819" h11="-10.92395969" h22="0.00000000" k00="0.13503645" k11="-0.12775008" k22="0.00000000"/>
</atom>
<atom symbol="Rn" lmax="2">
<local Zeff="8" radius="0.57000000" C1="14.62918461" C2="0.00000000" C3="0.00000000" C4="0.00000000"/>
<nonlocal l="0" radius="0.61518195" h00="0.98183224" h11="-1.03896274" h22="-0.12045584" k00="0.00000000" k11="0.00000000" k22="0.00000000"/>
<nonlocal l="1" radius="0.67669721" h00="0.61227859" h11="-0.34412231" h22="0.00000000" k00="0.54989620" k11="-0.02376028" k22="0.00000000"/>
<nonlocal l="2" radius="0.78833715" h00="0.55774596" h11="0.00000000" h22="0.00000000" k00="0.04548755" k11="0.00000000" k22="0.00000000"/>
</atom>
<atom symbol="Ru" lmax="2">
<local Zeff="8" radius="0.64721429" C1="8.68772333" C2="0.00000000" C3="0.00000000" C4="0.00000000"/>
<nonlocal l="0" radius="0.62565612" h00="1.63786602" h11="1.32933477" h22="0.00000000" k00="0.00000000" k11="0.00000000" k22="0.00000000"/>
<nonlocal l="1" radius="0.74642487" h00="0.63901157" h11="0.65037612" h22="0.00000000" k00="-0.09545431" k11="0.16425697" k22="0.00000000"/>
<nonlocal l="2" radius="0.44035802" h00="-4.88336495" h11="-3.06374629" h22="0.00000000" k00="0.04665238" k11="-0.06180814" k22="0.00000000"/>
</atom>
<atom symbol="Sb" lmax="2">
<local Zeff="5" radius="0.59000000" C1="6.68022783" C2="0.00000000" C3="0.00000000" C4="0.00000000"/>
<nonlocal l="0" radius="0.59768356" h00="1.95147672" h11="0.03753727" h22="-0.78663058" k00="0.00000000" k11="0.00000000" k22="0.00000000"/>
<nonlocal l="1" radius="0.67212205" h00="0.97031285" h11="-0.46673132" h22="0.00000000" k00="0.13922153" k11="0.02351298" k22="0.00000000"/>
<nonlocal l="2" radius="0.85655729" h00="0.30010262" h11="0.00000000" h22="0.00000000" k00="0.00943232" k11="0.00000000" k22="0.00000000"/>
</atom>
<atom symbol="Sc" lmax="2">
<local Zeff="3" radius="0.75000000" C1="0.00000000" C2="0.00000000" C3="0.00000000" C4="0.00000000"/>
<nonlocal l="0" radius="0.59707941" h00="1.83576833" h11="1.73430939" h22="1.41848330" k00="0.00000000" k11="0.00000000" k22="0.00000000"/>
<nonlocal l="1" radius="0.84799438" h00="0.78412669" h11="0.24673297" h22="0.00000000" k00="-0.00846271" k11="0.02091287" k22="0.00000000"/>
<nonlocal l="2" radius="0.45465318" h00="-3.85924078" h11="0.00000000" h22="0.00000000" k00="0.00142986" k11="0.00000000" k22="0.00000000"/>
</atom>
<atom symbol="Se" lmax="2">
<local Zeff="6" radius="0.51000000" C1="0.00000000" C2="0.00000000" C3="0.00000000" C4="0.00000000"/>
<nonlocal l="0" radius="0.43253108" h00="5.14513084" h11="2.05200900" h22="-1.36920317" k00="0.00000000" k11="0.00000000" k22="0.00000000"/>
<nonlocal l="1" radius="0.47247252" h00="2.85880607" h11="-0.59067050" h22="0.00000000" k00="0.06219585" k11="0.06490734" k22="0.00000000"/>
<nonlocal l="2" radius="0.61342013" h00="0.43482888" h11="0.00000000" h22="0.00000000" k00="0.00578395" k11="0.00000000" k22="0.00000000"/>
</atom>
<atom symbol="Si" lmax="1">
<local Zeff="4" radius="0.44000000" C1="-7.33610297" C2="0.00000000" C3="0.00000000" C4="0.00000000"/>
<nonlocal l="0" radius="0.42273813" h00="5.90692831" h11="3.25819622" h22="0.00000000" k00="0.00000000" k11="0.00000000" k22="0.00000000"/>
<nonlocal l="1" radius="0.48427842" h00="2.72701346" h11="0.00000000" h22="0.00000000" k00="0.00037280" k11="0.01443697" k22="0.00000000"/>
</atom>
<atom symbol="Sm" lmax="3">
<local Zeff="16" radius="0.52333337" C1="17.20679172" C2="-0.53280292" C3="0.00000000" C4="0.00000000"/>
<nonlocal l="0" radius="0.47967676" h00="1.72363519" h11="-2.65936731" h22="0.00000000" k00="0.00000000" k11="0.00000000" k22="0.00000000"/>
<nonlocal l="1" radius="0.49059775" h00="-0.08240311" h11="-1.11100858" h22="0.00000000" k00="-0.24029994" k11="1.20086678" k22="-1.05404138"/>
<nonlocal l="2" radius="0.47084026" h00="-0.41063034" h11="0.00000000" h22="0.00000000" k00="0.06335216" k11="0.00000000" k22="0.00000000"/>
<nonlocal l="3" radius="0.28404049" h00="-19.98429201" h11="0.00000000" h22="0.00000000" k00="0.01192432" k11="0.00000000" k22="0.00000000"/>
</atom>
<atom symbol="Sn" lmax="2">
<local Zeff="4" radius="0.60500000" C1="4.61091234" C2="0.00000000" C3="0.00000000" C4="0.00000000"/>
<nonlocal l="0" radius="0.66354369" h00="1.64879146" h11="-0.14197384" h22="-0.57654563" k00="0.00000000" k11="0.00000000" k22="0.00000000"/>
<nonlocal l="1" radius="0.74586492" h00="0.76935544" h11="-0.44507028" h22="0.00000000" k00="0.10393057" k11="0.00505735" k22="0.00000000"/>
<nonlocal l="2" radius="0.94445897" h00="0.22511508" h11="0.00000000" h22="0.00000000" k00="0.00706571" k11="0.00000000" k22="0.00000000"/>
</atom>
<atom symbol="Sr" lmax="2">
<local Zeff="2" radius="1.01000000" C1="0.68474888" C2="-0.06212465" C3="0.00000000" C4="0.00000000"/>
<nonlocal l="0" radius="0.83756431" h00="1.20039504" h11="0.92667525" h22="-0.31585755" k00="0.00000000" k11="0.00000000" k22="0.00000000"/>
<nonlocal l="1" radius="1.17417825" h00="0.43998339" h11="0.01826685" h22="0.00000000" k00="0.00402188" k11="0.02220714" k22="0.00000000"/>
<nonlocal l="2" radius="0.74317548" h00="-1.38699026" h11="0.00000000" h22="0.00000000" k00="0.00284555" k11="0.00000000" k22="0.00000000"/>
</atom>
<atom symbol="S" lmax="1">
<local Zeff="6" radius="0.42000000" C1="-6.55449184" C2="0.00000000" C3="0.00000000" C4="0.00000000"/>
<nonlocal l="0" radius="0.36175665" h00="7.90530250" h11="4.47169830" h22="0.00000000" k00="0.00000000" k11="0.00000000" k22="0.00000000"/>
<nonlocal l="1" radius="0.40528502" h00="3.86657900" h11="0.00000000" h22="0.00000000" k00="0.00537161" k11="0.02206245" k22="0.00000000"/>
</atom>
<atom symbol="Ta" lmax="2">
<local Zeff="5" radius="0.74400000" C1="3.62311645" C2="0.00000000" C3="0.00000000" C4="0.00000000"/>
<nonlocal l="0" radius="0.58180113" h00="2.00533833" h11="3.02703613" h22="0.00000000" k00="0.00000000" k11="0.00000000" k22="0.00000000"/>
<nonlocal l="1" radius="0.77064628" h00="0.51856664" h11="1.18537841" h22="0.00000000" k00="-0.48563525" k11="0.69514785" k22="0.00000000"/>
<nonlocal l="2" radius="0.53436996" h00="-2.20220040" h11="-1.66667495" h22="0.00000000" k00="0.08671559" k11="-0.09463501" k22="0.00000000"/>
</atom>
<atom symbol="Tb" lmax="3">
<local Zeff="19" radius="0.51458335" C1="17.60361623" C2="-0.82808004" C3="0.00000000" C4="0.00000000"/>
<nonlocal l="0" radius="0.44869439" h00="1.71848088" h11="-3.43523929" h22="0.00000000" k00="0.00000000" k11="0.00000000" k22="0.00000000"/>
<nonlocal l="1" radius="0.42422013" h00="0.56239978" h11="-2.78182671" h22="0.00000000" k00="-0.00872499" k11="1.14400661" k22="-0.86042467"/>
<nonlocal l="2" radius="0.48280866" h00="-0.62580219" h11="0.00000000" h22="0.00000000" k00="0.05175355" k11="0.00000000" k22="0.00000000"/>
<nonlocal l="3" radius="0.26825995" h00="-22.91169709" h11="0.00000000" h22="0.00000000" k00="0.01619671" k11="0.00000000" k22="0.00000000"/>
</atom>
<atom symbol="Tc" lmax="2">
<local Zeff="7" radius="0.67300000" C1="13.31538067" C2="0.00000000" C3="0.00000000" C4="0.00000000"/>
<nonlocal l="0" radius="0.67761188" h00="0.81921767" h11="0.34845968" h22="0.00000000" k00="0.00000000" k11="0.00000000" k22="0.00000000"/>
<nonlocal l="1" radius="0.78427538" h00="0.02867266" h11="0.65836292" h22="0.00000000" k00="-0.08075975" k11="0.14066787" k22="0.00000000"/>
<nonlocal l="2" radius="0.51988975" h00="-5.98422427" h11="0.72182246" h22="0.00000000" k00="0.02602474" k11="-0.04177619" k22="0.00000000"/>
</atom>
<atom symbol="Te" lmax="2">
<local Zeff="6" radius="0.57500000" C1="9.38708481" C2="0.00000000" C3="0.00000000" C4="0.00000000"/>
<nonlocal l="0" radius="0.55645602" h00="2.04689031" h11="-0.02933260" h22="-0.88111927" k00="0.00000000" k11="0.00000000" k22="0.00000000"/>
<nonlocal l="1" radius="0.61526187" h00="1.03347754" h11="-0.48117240" h22="0.00000000" k00="0.17299713" k11="0.05064130" k22="0.00000000"/>
<nonlocal l="2" radius="0.80510072" h00="0.31741073" h11="0.00000000" h22="0.00000000" k00="0.01080862" k11="0.00000000" k22="0.00000000"/>
</atom>
<atom symbol="Ti" lmax="2">
<local Zeff="4" radius="0.72000000" C1="0.00000000" C2="0.00000000" C3="0.00000000" C4="0.00000000"/>
<nonlocal l="0" radius="0.52841076" h00="1.86661330" h11="1.44023325" h22="3.65817177" k00="0.00000000" k11="0.00000000" k22="0.00000000"/>
<nonlocal l="1" radius="0.79114554" h00="0.96791577" h11="0.26068669" h22="0.00000000" k00="-0.00933253" k11="0.02529075" k22="0.00000000"/>
<nonlocal l="2" radius="0.40871178" h00="-4.82645635" h11="0.00000000" h22="0.00000000" k00="0.00200953" k11="0.00000000" k22="0.00000000"/>
</atom>
<atom symbol="Tl" lmax="2">
<local Zeff="3" radius="0.63000000" C1="-1.23584552" C2="0.00000000" C3="0.00000000" C4="0.00000000"/>
<nonlocal l="0" radius="0.75400547" h00="1.87576571" h11="-0.30367964" h22="-0.78133689" k00="0.00000000" k11="0.00000000" k22="0.00000000"/>
<nonlocal l="1" radius="0.90374170" h00="0.75966830" h11="-0.58672051" h22="0.00000000" k00="0.16864149" k11="0.00445921" k22="0.00000000"/>
<nonlocal l="2" radius="1.06351212" h00="0.24761396" h11="0.00000000" h22="0.00000000" k00="0.02294091" k11="0.00000000" k22="0.00000000"/>
</atom>
<atom symbol="Tm" lmax="3">
<local Zeff="23" radius="0.50291669" C1="17.24729254" C2="-1.62769708" C3="0.00000000" C4="0.00000000"/>
<nonlocal l="0" radius="0.41337286" h00="1.94719583" h11="-4.12155644" h22="0.00000000" k00="0.00000000" k11="0.00000000" k22="0.00000000"/>
<nonlocal l="1" radius="0.40992301" h00="-0.09449281" h11="-2.22408718" h22="0.00000000" k00="2.04536983" k11="-2.34723738" k22="1.90273579"/>
<nonlocal l="2" radius="0.39287009" h00="-1.35330770" h11="0.00000000" h22="0.00000000" k00="0.11929895" k11="0.00000000" k22="0.00000000"/>
<nonlocal l="3" radius="0.24391696" h00="-28.10415875" h11="0.00000000" h22="0.00000000" k00="0.02383347" k11="0.00000000" k22="0.00000000"/>
</atom>
<atom symbol="V" lmax="2">
<local Zeff="5" radius="0.69000000" C1="0.00000000" C2="0.00000000" C3="0.00000000" C4="0.00000000"/>
<nonlocal l="0" radius="0.51470421" h00="2.20866978" h11="1.89676307" h22="3.07637723" k00="0.00000000" k11="0.00000000" k22="0.00000000"/>
<nonlocal l="1" radius="0.74350381" h00="1.11575121" h11="0.28664887" h22="0.00000000" k00="-0.01097329" k11="0.03081565" k22="0.00000000"/>
<nonlocal l="2" radius="0.37488959" h00="-5.84163317" h11="0.00000000" h22="0.00000000" k00="0.00271707" k11="0.00000000" k22="0.00000000"/>
</atom>
<atom symbol="W" lmax="2">
<local Zeff="6" radius="0.71900000" C1="4.05844991" C2="0.00000000" C3="0.00000000" C4="0.00000000"/>
<nonlocal l="0" radius="0.58246289" h00="2.16116556" h11="2.74149991" h22="0.00000000" k00="0.00000000" k11="0.00000000" k22="0.00000000"/>
<nonlocal l="1" radius="0.74230741" h00="0.60097339" h11="1.29994284" h22="0.00000000" k00="-0.50979956" k11="0.75173934" k22="0.00000000"/>
<nonlocal l="2" radius="0.53495887" h00="-2.51706347" h11="-0.78913661" h22="0.00000000" k00="0.07577234" k11="-0.08619292" k22="0.00000000"/>
</atom>
<atom symbol="Xe" lmax="2">
<local Zeff="8" radius="0.56000000" C1="12.73427972" C2="0.00000000" C3="0.00000000" C4="0.00000000"/>
<nonlocal l="0" radius="0.50737118" h00="2.23645069" h11="-0.40355073" h22="-1.13250655" k00="0.00000000" k11="0.00000000" k22="0.00000000"/>
<nonlocal l="1" radius="0.54102371" h00="1.13004299" h11="-0.75276413" h22="0.00000000" k00="0.23660318" k11="0.10847345" k22="0.00000000"/>
<nonlocal l="2" radius="0.72982111" h00="0.28013078" h11="0.00000000" h22="0.00000000" k00="0.01336223" k11="0.00000000" k22="0.00000000"/>
</atom>
<atom symbol="Yb" lmax="3">
<local Zeff="24" radius="0.50000000" C1="17.35714421" C2="-1.77391642" C3="0.00000000" C4="0.00000000"/>
<nonlocal l="0" radius="0.40230918" h00="2.12077095" h11="-4.80298999" h22="0.00000000" k00="0.00000000" k11="0.00000000" k22="0.00000000"/>
<nonlocal l="1" radius="0.41435774" h00="-0.92321216" h11="-1.67853959" h22="0.00000000" k00="-0.34946961" k11="2.07429479" k22="-1.81429663"/>
<nonlocal l="2" radius="0.44402468" h00="-0.88996733" h11="0.00000000" h22="0.00000000" k00="0.07007567" k11="0.00000000" k22="0.00000000"/>
<nonlocal l="3" radius="0.23829829" h00="-29.93285367" h11="0.00000000" h22="0.00000000" k00="0.02571848" k11="0.00000000" k22="0.00000000"/>
</atom>
<atom symbol="Y" lmax="2">
<local Zeff="3" radius="0.90000000" C1="-0.34389132" C2="0.00000000" C3="0.00000000" C4="0.00000000"/>
<nonlocal l="0" radius="0.78245699" h00="1.52065466" h11="1.48436836" h22="-0.18901334" k00="0.00000000" k11="0.00000000" k22="0.00000000"/>
<nonlocal l="1" radius="0.94986375" h00="0.78095000" h11="0.36873894" h22="0.00000000" k00="-0.04333632" k11="0.07998905" k22="0.00000000"/>
<nonlocal l="2" radius="0.65385060" h00="-1.25692979" h11="-0.07536797" h22="0.00000000" k00="0.00919822" k11="-0.01165653" k22="0.00000000"/>
</atom>
<atom symbol="Zn" lmax="2">
<local Zeff="2" radius="0.57000000" C1="0.00000000" C2="0.00000000" C3="0.00000000" C4="0.00000000"/>
<nonlocal l="0" radius="0.64071219" h00="2.08855724" h11="-0.21827024" h22="-0.94131659" k00="0.00000000" k11="0.00000000" k22="0.00000000"/>
<nonlocal l="1" radius="0.96760483" h00="0.16354600" h11="-0.22708635" h22="0.00000000" k00="0.01213948" k11="-0.00487568" k22="0.00000000"/>
<nonlocal l="2" radius="1.33035200" h00="0.01048578" h11="0.00000000" h22="0.00000000" k00="0.00022546" k11="0.00000000" k22="0.00000000"/>
</atom>
<atom symbol="Zr" lmax="2">
<local Zeff="4" radius="0.75000000" C1="-0.78261098" C2="0.00000000" C3="0.00000000" C4="0.00000000"/>
<nonlocal l="0" radius="0.64999821" h00="1.73987747" h11="2.38820846" h22="1.20534876" k00="0.00000000" k11="0.00000000" k22="0.00000000"/>
<nonlocal l="1" radius="0.87440769" h00="1.01829381" h11="0.52822332" h22="0.00000000" k00="-0.05748649" k11="0.10449452" k22="0.00000000"/>
<nonlocal l="2" radius="0.63066761" h00="-1.17391057" h11="0.21217861" h22="0.00000000" k00="0.00938027" k11="-0.01197300" k22="0.00000000"/>
</atom>
